s3_tarball_manager/__init__.py
s3_tarball_manager/manager.py
tests/__init__.py
tests/test_manager.py
s3_tarball_manager-0.1.0.dist-info/LICENSE
s3_tarball_manager-0.1.0.dist-info/METADATA
s3_tarball_manager-0.1.0.dist-info/WHEEL
s3_tarball_manager-0.1.0.dist-info/top_level.txt
s3_tarball_manager-0.1.0.dist-info/RECORD
